aiZero/__init__.py
aiZero/static/.DS_Store
aiZero/static/favicon.ico
aiZero/static/js/marked.min.js
aiZero/static/vendor/.DS_Store
aiZero/static/vendor/fontawesome/.DS_Store
aiZero/static/vendor/fontawesome/css/all.css
aiZero/static/vendor/fontawesome/css/all.min.css
aiZero/static/vendor/fontawesome/css/brands.css
aiZero/static/vendor/fontawesome/css/brands.min.css
aiZero/static/vendor/fontawesome/css/fontawesome.css
aiZero/static/vendor/fontawesome/css/fontawesome.min.css
aiZero/static/vendor/fontawesome/css/regular.css
aiZero/static/vendor/fontawesome/css/regular.min.css
aiZero/static/vendor/fontawesome/css/solid.css
aiZero/static/vendor/fontawesome/css/solid.min.css
aiZero/static/vendor/fontawesome/css/svg-with-js.css
aiZero/static/vendor/fontawesome/css/svg-with-js.min.css
aiZero/static/vendor/fontawesome/css/v4-font-face.css
aiZero/static/vendor/fontawesome/css/v4-font-face.min.css
aiZero/static/vendor/fontawesome/css/v4-shims.css
aiZero/static/vendor/fontawesome/css/v4-shims.min.css
aiZero/static/vendor/fontawesome/css/v5-font-face.css
aiZero/static/vendor/fontawesome/css/v5-font-face.min.css
aiZero/static/vendor/fontawesome/webfonts/fa-brands-400.ttf
aiZero/static/vendor/fontawesome/webfonts/fa-brands-400.woff2
aiZero/static/vendor/fontawesome/webfonts/fa-regular-400.ttf
aiZero/static/vendor/fontawesome/webfonts/fa-regular-400.woff2
aiZero/static/vendor/fontawesome/webfonts/fa-solid-900.ttf
aiZero/static/vendor/fontawesome/webfonts/fa-solid-900.woff2
aiZero/static/vendor/fontawesome/webfonts/fa-v4compatibility.ttf
aiZero/static/vendor/fontawesome/webfonts/fa-v4compatibility.woff2
aiZero/templates/index.html
aiZero/templates/index_modern.html
aizero-0.0.7a0.dist-info/METADATA
aizero-0.0.7a0.dist-info/WHEEL
aizero-0.0.7a0.dist-info/top_level.txt
aizero-0.0.7a0.dist-info/RECORD
