Metadata-Version: 2.4
Name: aiZero
Version: 0.0.7a0
Summary: A simple and easy-to-use library that connects to common artificial intelligence interfaces, allowing for quick development of local web applications. It includes mainstream AI capabilities such as LLM text interaction, image understanding, audio understanding, image generation, speech recognition, and speech synthesis.
Author: emhang
Author-email: emhang@126.com
Requires-Python: >=3.6
Requires-Dist: flask>=3.0.0
Requires-Dist: requests
Requires-Dist: dashscope==1.13.6
Requires-Dist: openai>=1.0.0
Requires-Dist: pillow
Dynamic: author
Dynamic: author-email
Dynamic: description
Dynamic: description-content-type
Dynamic: requires-dist
Dynamic: requires-python
Dynamic: summary
